{
  "name": "Emilie Gomez",
  "age": 21,
  "address": {
    "street": "Nihrin Turnpike",
    "city": "Ejuawno",
    "state": "MN",
    "zip": "23040"
  },
  "contact": {
    "phone": "(833) 416-7790",
    "servicePhone": "800585119"
  },
  "birthday": "1972-12-19T09:24:59.519Z",
  "ip": "230.170.83.169",
  "foo": "bar",
  "profile": {
    "about": "Hivmes bacum uce fu hijahej mujo zaz de jurnogiw osrandu sedkeru suj jibesfik. Uzebawu fo hib dakacva zuwajo ezaon mizcef sum tugote jakipokuv kabi guanu cugok kuojdo vuspirfup laceuvu zadwefvul go. Hog alas gicamtom lidjod pago tedcispi icotu ca rautlu zawu ari zem ez sura ocul uzakujvu tucor zeto. Ki wadmiaf wuz dutfi icekev jeteka ifieb wopu welzekej viskiho da bow. Imiucgah wecamwu notada pahub venen kidhuto vevfelfew ritir ce pe fanabufe hev agum uma sokrened fumatoced zucpamtiv diljum. Remema kibosfe fijaf kal cusiknuj pajej wa kiovnaf miru tiewoli jozsamol lonjagmil wauk jelokod.",
    "bio": "Vijku waz usubaba salza lauwekeb vim tod gerwebop tor awuzuda vecec jejpe. Fas ja oftojri fuzvom koblo teducbe zuzitgu ro to jo wog na zam. Utudek ci ru nozipom com tuuru cena sih kekalbe dabkipeta agiitilu wehdoci po cuzokebi ezbew juzaco."
  },
  "apiKey": "3e2dfaeeeed1477051d43ae62ab29cc8a4ad25f2df5b9911750775acfe9781d0",
  "currency": {
    "code": "ZMW",
    "name": "Zambia Kwacha"
  }
}