{
  "name": "Elmer Brown",
  "age": 35,
  "address": {
    "street": "Ligzeb Manor",
    "city": "Rozice",
    "state": "ID",
    "zip": "04584"
  },
  "contact": {
    "phone": "(215) 504-7287",
    "servicePhone": "800772938"
  },
  "birthday": "1974-12-11T22:26:35.141Z",
  "ip": "35.153.106.42",
  "foo": "bar",
  "profile": {
    "about": "Kasenijaj aje sod zo puw ru liuv lade becawle urowa gonu miwuwku ruj wo couv sezic. Olicistig cuzpil log behir piobu ge zo wohos cujapcaw juc ini hotmorog fepose tu watebis keritjet. Mokrebuve sasi bemes meto bapi nahta kob rog iwreziwu ceru irdas bagraphe wesel osufufod wifeliku men.",
    "bio": "Cutacah muffo tuhebo olo ram ruto iwowog imo biidama raren opait niotiawo kaum mapjoka wunicha. Vas tu folillol fu dazof razbo pajpor cacun cafepi geeco ahpu ja ivaha adur towicta. Cahow fikasle coche zihe diddimtuc losotpaz zatpi raekuehe obugpun nizre rigbu eldozih pet jo. Fipeasi tor culutu civtoehe ewilic vof wiruv dod liboje lunjok podpo neb dejelzi no. Poub wi pafada eluje vuwnullob epaonako pujla bez cipbipde civwouk nitzoc wageug jiulebe ko puclud fub zak vosodik. Hid wosnulde hizuto jujweeki ipu welagak utfo uhoava guvori no wa coepa ugeaju."
  },
  "apiKey": "e6ec6660fc878d0fbed0da963c3bbba156c91879f98556ec34d9a596783aae39",
  "currency": {
    "code": "MDL",
    "name": "Moldova Leu"
  }
}